{"_id":"Skdmx1BGf","title":"hql进行数据的封装 只查询部分字段 封装成其他对象","body":{"entityMap":{},"blocks":[{"key":"ag6qs","text":"hql进行数据的封装 只查询部分字段 封装成其他对象","type":"header-two","depth":0,"inlineStyleRanges":[],"entityRanges":[],"data":{}},{"key":"22j3b","text":"String hql = \"select new Test(id,name,foreignKeyId) from Link\";    ","type":"custom-code-block-java","depth":0,"inlineStyleRanges":[],"entityRanges":[],"data":{}},{"key":"59kd9","text":"","type":"unstyled","depth":0,"inlineStyleRanges":[],"entityRanges":[],"data":{}}]},"dateCreated":"2017-12-18T06:28:48.074Z","lastUpdated":"2017-12-18T06:29:00.482Z","notebookId":"HkfhF54zz"}
