{"_id":"r1Ci5w5lG","title":"scp 命令","body":{"blocks":[{"data":{},"depth":0,"entityRanges":[],"inlineStyleRanges":[],"key":"ag6qs","text":"scp 命令","type":"unstyled"},{"data":{},"depth":0,"entityRanges":[],"inlineStyleRanges":[],"key":"61jms","text":"==================","type":"unstyled"},{"data":{},"depth":0,"entityRanges":[],"inlineStyleRanges":[],"key":"96ivr","text":"scp 可以在 2个 linux 主机间复制文件；","type":"unstyled"},{"data":{},"depth":0,"entityRanges":[],"inlineStyleRanges":[],"key":"3j2r4","text":"命令基本格式： ","type":"unstyled"},{"data":{},"depth":0,"entityRanges":[],"inlineStyleRanges":[],"key":"eb95u","text":"      scp [可选参数] file_source file_target","type":"unstyled"},{"data":{},"depth":0,"entityRanges":[],"inlineStyleRanges":[],"key":"f57lj","text":"======","type":"unstyled"},{"data":{},"depth":0,"entityRanges":[],"inlineStyleRanges":[],"key":"8thic","text":"从 本地 复制到 远程","type":"unstyled"},{"data":{},"depth":0,"entityRanges":[],"inlineStyleRanges":[],"key":"fhonm","text":"======","type":"unstyled"},{"data":{},"depth":0,"entityRanges":[],"inlineStyleRanges":[],"key":"as30p","text":"* 复制文件：","type":"unstyled"},{"data":{},"depth":0,"entityRanges":[],"inlineStyleRanges":[],"key":"diqm4","text":"        * 命令格式：","type":"unstyled"},{"data":{},"depth":0,"entityRanges":[],"inlineStyleRanges":[],"key":"2t5jv","text":"    scp local_file remote_username@remote_ip:remote_folder","type":"custom-code-block-vim"},{"data":{},"depth":0,"entityRanges":[],"inlineStyleRanges":[],"key":"tedf","text":"                或者","type":"unstyled"},{"data":{},"depth":0,"entityRanges":[],"inlineStyleRanges":[],"key":"39emg","text":"   scp local_file remote_username@remote_ip:remote_file","type":"custom-code-block-vim"},{"data":{},"depth":0,"entityRanges":[],"inlineStyleRanges":[],"key":"civo0","text":"                或者","type":"unstyled"},{"data":{},"depth":0,"entityRanges":[],"inlineStyleRanges":[],"key":"eu60c","text":"  scp local_file remote_ip:remote_folder","type":"custom-code-block-vim"},{"data":{},"depth":0,"entityRanges":[],"inlineStyleRanges":[],"key":"ej04t","text":"                或者","type":"unstyled"},{"data":{},"depth":0,"entityRanges":[],"inlineStyleRanges":[],"key":"73rac","text":"  scp local_file remote_ip:remote_file","type":"custom-code-block-vim"},{"data":{},"depth":0,"entityRanges":[],"inlineStyleRanges":[],"key":"3qpfl","text":"","type":"unstyled"},{"data":{},"depth":0,"entityRanges":[],"inlineStyleRanges":[],"key":"2fiki","text":"                第1,2个指定了用户名，命令执行后需要再输入密码，第1个仅指定了远程的目录，文件名字不变，第2个指定了文件名；","type":"unstyled"},{"data":{},"depth":0,"entityRanges":[],"inlineStyleRanges":[],"key":"fv4rm","text":"                第3,4个没有指定用户名，命令执行后需要输入用户名和密码，第3个仅指定了远程的目录，文件名字不变，第4个指定了文件名；","type":"unstyled"},{"data":{},"depth":0,"entityRanges":[],"inlineStyleRanges":[],"key":"1eirp","text":"        * 例子：","type":"unstyled"},{"data":{},"depth":0,"entityRanges":[],"inlineStyleRanges":[],"key":"tjkr","text":"    scp /home/space/music/1.mp3 root@www.cumt.edu.cn:/home/root/others/music","type":"custom-code-block-vim"},{"data":{},"depth":0,"entityRanges":[],"inlineStyleRanges":[],"key":"8mite","text":"    scp /home/space/music/1.mp3 root@www.cumt.edu.cn:/home/root/others/music/001.mp3","type":"custom-code-block-vim"},{"data":{},"depth":0,"entityRanges":[],"inlineStyleRanges":[],"key":"8633g","text":"     scp /home/space/music/1.mp3 www.cumt.edu.cn:/home/root/others/music","type":"custom-code-block-vim"},{"data":{},"depth":0,"entityRanges":[],"inlineStyleRanges":[],"key":"dijdg","text":"     scp /home/space/music/1.mp3 www.cumt.edu.cn:/home/root/others/music/001.mp3","type":"custom-code-block-vim"},{"data":{},"depth":0,"entityRanges":[],"inlineStyleRanges":[],"key":"165gi","text":"","type":"unstyled"},{"data":{},"depth":0,"entityRanges":[],"inlineStyleRanges":[],"key":"222h1","text":"* 复制目录：","type":"unstyled"},{"data":{},"depth":0,"entityRanges":[],"inlineStyleRanges":[],"key":"7408e","text":"        * 命令格式：","type":"unstyled"},{"data":{},"depth":0,"entityRanges":[],"inlineStyleRanges":[],"key":"fqa5m","text":"   scp -r local_folder remote_username@remote_ip:remote_folder","type":"custom-code-block-vim"},{"data":{},"depth":0,"entityRanges":[],"inlineStyleRanges":[],"key":"bgl7r","text":"                或者","type":"unstyled"},{"data":{},"depth":0,"entityRanges":[],"inlineStyleRanges":[],"key":"fosm","text":"   scp -r local_folder remote_ip:remote_folder","type":"custom-code-block-vim"},{"data":{},"depth":0,"entityRanges":[],"inlineStyleRanges":[],"key":"3t256","text":"","type":"unstyled"},{"data":{},"depth":0,"entityRanges":[],"inlineStyleRanges":[],"key":"4htb0","text":"                第1个指定了用户名，命令执行后需要再输入密码；","type":"unstyled"},{"data":{},"depth":0,"entityRanges":[],"inlineStyleRanges":[],"key":"6o8ef","text":"                第2个没有指定用户名，命令执行后需要输入用户名和密码；","type":"unstyled"},{"data":{},"depth":0,"entityRanges":[],"inlineStyleRanges":[],"key":"8uupo","text":"        * 例子：","type":"unstyled"},{"data":{},"depth":0,"entityRanges":[],"inlineStyleRanges":[],"key":"4pp9d","text":"    scp -r /home/space/music/ root@www.cumt.edu.cn:/home/root/others/","type":"custom-code-block-vim"},{"data":{},"depth":0,"entityRanges":[],"inlineStyleRanges":[],"key":"8e60l","text":"    scp -r /home/space/music/ www.cumt.edu.cn:/home/root/others/","type":"custom-code-block-vim"},{"data":{},"depth":0,"entityRanges":[],"inlineStyleRanges":[],"key":"d11pv","text":"","type":"unstyled"},{"data":{},"depth":0,"entityRanges":[],"inlineStyleRanges":[],"key":"1b5o1","text":"                上面 命令 将 本地 music 目录 复制 到 远程 others 目录下，即复制后有 远程 有 ../others/music/ 目录","type":"unstyled"},{"data":{},"depth":0,"entityRanges":[],"inlineStyleRanges":[],"key":"17lbo","text":"当你幸福的时候，我不在，当我幸福的时候，你也不在","type":"unstyled"}],"entityMap":{}},"dateCreated":"2017-11-28T04:48:38.315Z","lastUpdated":"2017-12-18T06:36:35.957Z","notebookId":"rJx8zxrxf"}
